doctest_docutils.py
docutils_compat.py
gp_libs.py
linkify_issues.py
pytest_doctest_docutils.py
gp_libs-0.0.17.dist-info/METADATA
gp_libs-0.0.17.dist-info/WHEEL
gp_libs-0.0.17.dist-info/entry_points.txt
gp_libs-0.0.17.dist-info/licenses/LICENSE
gp_libs-0.0.17.dist-info/RECORD
