Metadata-Version: 2.4
Name: gp-libs
Version: 0.0.17
Summary: Internal utilities for projects following git-pull python package spec
Project-URL: Bug Tracker, https://github.com/git-pull/gp-libs/issues
Project-URL: Documentation, https://gp-libs.git-pull.com
Project-URL: Repository, https://github.com/git-pull/gp-libs
Project-URL: Changes, https://github.com/git-pull/gp-libs/blob/master/CHANGES
Author-email: Tony Narlock <tony@git-pull.com>
License: MIT
License-File: LICENSE
Classifier: Development Status :: 4 - Beta
Classifier: Environment :: Web Environment
Classifier: Framework :: Pytest
Classifier: Intended Audience :: Developers
Classifier: License :: OSI Approved :: MIT License
Classifier: Operating System :: MacOS :: MacOS X
Classifier: Operating System :: POSIX
Classifier: Programming Language :: Python
Classifier: Programming Language :: Python :: 3
Classifier: Programming Language :: Python :: 3.10
Classifier: Programming Language :: Python :: 3.11
Classifier: Programming Language :: Python :: 3.12
Classifier: Programming Language :: Python :: 3.13
Classifier: Programming Language :: Python :: 3.14
Classifier: Topic :: System :: Shells
Classifier: Topic :: Utilities
Requires-Python: <4.0,>=3.10
Requires-Dist: docutils
Requires-Dist: myst-parser
